{
	"name": "Lego_HTTP_to_ADLS_Themes",
	"properties": {
		"description": "Lego_HTTP_to_ADLS_Themes",
		"activities": [
			{
				"name": "Copy_css",
				"type": "Copy",
				"dependsOn": [],
				"policy": {
					"timeout": "7.00:00:00",
					"retry": 0,
					"retryIntervalInSeconds": 30,
					"secureOutput": false,
					"secureInput": false
				},
				"userProperties": [
					{
						"name": "Source",
						"value": "themes.csv.gz"
					},
					{
						"name": "Destination",
						"value": "lego//themes.csv"
					}
				],
				"typeProperties": {
					"source": {
						"type": "DelimitedTextSource",
						"storeSettings": {
							"type": "HttpReadSettings",
							"requestMethod": "GET"
						},
						"formatSettings": {
							"type": "DelimitedTextReadSettings",
							"skipLineCount": 0
						}
					},
					"sink": {
						"type": "DelimitedTextSink",
						"storeSettings": {
							"type": "AzureBlobFSWriteSettings"
						},
						"formatSettings": {
							"type": "DelimitedTextWriteSettings",
							"quoteAllText": true,
							"fileExtension": ".txt"
						}
					},
					"enableStaging": false,
					"enableSkipIncompatibleRow": true,
					"logSettings": {
						"enableCopyActivityLog": true,
						"copyActivityLogSettings": {
							"logLevel": "Warning",
							"enableReliableLogging": false
						},
						"logLocationSettings": {
							"linkedServiceName": {
								"referenceName": "AzureDataLakeStorage1",
								"type": "LinkedServiceReference"
							},
							"path": "lego/errors/themes"
						}
					}
				},
				"inputs": [
					{
						"referenceName": "SourceDataset_css",
						"type": "DatasetReference"
					}
				],
				"outputs": [
					{
						"referenceName": "DestinationDataset_css",
						"type": "DatasetReference"
					}
				]
			}
		],
		"annotations": []
	}
}